odoo/addons/payment_mode_report_invoice/__init__.py
odoo/addons/payment_mode_report_invoice/__manifest__.py
odoo/addons/payment_mode_report_invoice/i18n/ca_ES.po
odoo/addons/payment_mode_report_invoice/i18n/es.po
odoo/addons/payment_mode_report_invoice/i18n/eu_ES.po
odoo/addons/payment_mode_report_invoice/i18n/fr.po
odoo/addons/payment_mode_report_invoice/views/report_invoice.xml
odoo14_addon_payment_mode_report_invoice-14.0.1.0.0.dist-info/METADATA
odoo14_addon_payment_mode_report_invoice-14.0.1.0.0.dist-info/WHEEL
odoo14_addon_payment_mode_report_invoice-14.0.1.0.0.dist-info/top_level.txt
odoo14_addon_payment_mode_report_invoice-14.0.1.0.0.dist-info/RECORD
